kardiasclean/__init__.py
kardiasclean/clean.py
kardiasclean/create.py
kardiasclean/info.py
kardiasclean/normalize.py
kardiasclean/pre_processing.py
kardiasclean/tokenizer.py
kardiasclean-0.3.3.dist-info/LICENSE
kardiasclean-0.3.3.dist-info/WHEEL
kardiasclean-0.3.3.dist-info/METADATA
kardiasclean-0.3.3.dist-info/RECORD
