Metadata-Version: 2.1
Name: kardiasclean
Version: 0.3.3
Summary: Medical Records Normalizer
Home-page: https://github.com/AlbertoV5/kardiasclean
License: MIT
Author: AlbertoV5
Author-email: 58243333+AlbertoV5@users.noreply.github.com
Requires-Python: >=3.7.6,<3.11
Classifier: License :: OSI Approved :: MIT License
Classifier: Programming Language :: Python :: 3
Classifier: Programming Language :: Python :: 3.8
Classifier: Programming Language :: Python :: 3.9
Classifier: Programming Language :: Python :: 3.10
Requires-Dist: nltk (>=3.7,<4.0)
Requires-Dist: numpy (>=1.21.6,<2.0.0)
Requires-Dist: pandas (>=1.3.5,<2.0.0)
Requires-Dist: phonetics (>=1.0.5,<2.0.0)
Project-URL: Documentation, https://albertov5.github.io/kardiasclean
Project-URL: Repository, https://github.com/AlbertoV5/kardiasclean
